niton_tools/__init__.py
niton_tools/niton_measurement_dict.csv
niton_tools/niton_tools.py
niton_tools-0.2.1.dist-info/licenses/LICENSE.txt
niton_tools-0.2.1.dist-info/METADATA
niton_tools-0.2.1.dist-info/WHEEL
niton_tools-0.2.1.dist-info/top_level.txt
niton_tools-0.2.1.dist-info/RECORD
