Metadata-Version: 2.4
Name: niton-tools
Version: 0.2.1
Summary: Manage data from Niton XRF analyzers
Home-page: https://github.com/sarttiso/niton-tools
Author: Adrian Tasistro-Hart
Author-email: adrian@tasistro-hart.com
License: GPL-3.0-only
Project-URL: Source, https://github.com/sarttiso/niton-tools
Project-URL: Changelog, https://github.com/sarttiso/niton-tools/blob/main/changelog.md
Platform: any
Classifier: Development Status :: 4 - Beta
Classifier: Programming Language :: Python :: 3
License-File: LICENSE.txt
Requires-Dist: importlib-metadata; python_version < "3.8"
Requires-Dist: pandas
Requires-Dist: openpyxl
Requires-Dist: numpy
Requires-Dist: scipy
Requires-Dist: geochemdb
Requires-Dist: ipyfilechooser
Requires-Dist: ipywidgets
Requires-Dist: matplotlib
Dynamic: license-file
